{"version":1,"notes":"","documentation":"\"This file is a QMK Configurator export. You can import this at <https://config.qmk.fm>. It can also be used directly with QMK's source code.\n\nTo setup your QMK environment check out the tutorial: <https://docs.qmk.fm/#/newbs>\n\nYou can convert this file to a keymap.c using this command: `qmk json2c {keymap}`\n\nYou can compile this keymap using this command: `qmk compile {keymap}`\"\n","keyboard":"keebio/bdn9/rev2","keymap":"hello_there","layout":"LAYOUT","layers"
:[["TO(1)","TO(7)","TO(5)", "KC_DEL","KC_UP","KC_ENT", "KC_LEFT"," KC_DOWN"," KC_RGHT"],
["TO(2) "," KC_BTN3" , "TO(0) ","KC_BTN1 ", "KC_MS_U "," KC_BTN2 "," KC_MS_L" , "KC_MS_D" ," KC_MS_R"],
["TO(3)" ," TD(TD_CP)" , "TO(1)"," KC_B" ," KC_P" ," KC_E","KC_LEFT_ANGLE_BRACKET" ," KC_X" ," KC_RIGHT_ANGLE_BRACKET"],
["TO(4) "," MO(0) "," TO(2)","KC_W ", "KC_M "," KC_V", "  LCTL(A) ", "LCTL(D)" ," LCTL(T)"],
[" TO(5)" , "TO(0)" ," TO(3)","KC_F1" , "KC_F2" , "KC_F3" , "KC_F4" ," KC_F5" , "KC_F6"],
["  TO(0) "," KC_RSHIFT","TO(4) ","RGB_TOG "," BL_STEP "," RGB_SAI "," RGB_MOD "," BL_TOGG "," RGB_SPI"]],"author":""}